{
  "nodes": [
    {
      "parameters": {
        "httpMethod": "POST",
        "path": "impulsis-close-origin",
        "responseMode": "responseNode",
        "options": {}
      },
      "id": "b1b2ccd3-70f3-472a-aa76-b1307999ccdd",
      "name": "Webhook Fechar Origem",
      "type": "n8n-nodes-base.webhook",
      "typeVersion": 2,
      "position": [
        -672,
        256
      ],
      "webhookId": "8d39725e-00b1-48ff-aab5-107fef166f03"
    },
    {
      "parameters": {
        "respondWith": "json",
        "responseBody": "={{ { \"status\": \"ok\" } }}",
        "options": {}
      },
      "id": "eb13b921-d8fc-41a6-bfb3-28292604c0b3",
      "name": "Resposta 200 Antiga - Desconectada",
      "type": "n8n-nodes-base.respondToWebhook",
      "typeVersion": 1,
      "position": [
        -720,
        352
      ]
    },
    {
      "parameters": {
        "jsCode": "const wh = $input.first().json;\nconst b = wh.body || {};\n\nconst action = String(b.action || '').trim();\nconst child_ticket_id = String(b.child_ticket_id || '').trim();\nconst origin_ticket_id = String(b.origin_ticket_id || '').trim();\n\nconst acceptedActions = ['close_origin', 'child_solved', 'child_closed', ''];\n\nlet validation_error = null;\nif (!acceptedActions.includes(action)) {\n  validation_error = 'invalid_action';\n} else if (!origin_ticket_id || origin_ticket_id === '0') {\n  validation_error = 'invalid_origin_ticket_id';\n} else if (!child_ticket_id || child_ticket_id === '0') {\n  validation_error = 'invalid_child_ticket_id';\n} else if (origin_ticket_id === child_ticket_id) {\n  validation_error = 'origin_and_child_are_same_ticket';\n}\n\nreturn [{ json: {\n  action,\n  child_ticket_id,\n  origin_ticket_id,\n  agent_name: b.agent_name || '',\n  agent_email: b.agent_email || '',\n  payload_valid: !validation_error,\n  validation_error\n} }];"
      },
      "id": "360667e4-f326-4e75-b24a-19227c75c1ac",
      "name": "Extrair Dados do Webhook",
      "type": "n8n-nodes-base.code",
      "typeVersion": 2,
      "position": [
        -448,
        256
      ]
    },
    {
      "parameters": {
        "conditions": {
          "options": {
            "caseSensitive": true,
            "leftValue": "",
            "typeValidation": "strict",
            "version": 2
          },
          "conditions": [
            {
              "id": "cond-payload-valid",
              "leftValue": "={{ $json.payload_valid }}",
              "rightValue": true,
              "operator": {
                "type": "boolean",
                "operation": "equals"
              }
            }
          ],
          "combinator": "and"
        },
        "options": {}
      },
      "id": "19b182d6-ac99-410c-a2a9-c31b2f3f5948",
      "name": "Payload Valido",
      "type": "n8n-nodes-base.if",
      "typeVersion": 2,
      "position": [
        -224,
        256
      ]
    },
    {
      "parameters": {
        "method": "PUT",
        "url": "=https://webposto.zendesk.com/api/v2/tickets/{{ $('Extrair Dados do Webhook').first().json.origin_ticket_id }}.json",
        "authentication": "genericCredentialType",
        "genericAuthType": "httpHeaderAuth",
        "sendBody": true,
        "specifyBody": "json",
        "jsonBody": "={{ JSON.stringify({ ticket: { status: 'solved', additional_tags: ['impulsis_origem_fechada'], custom_fields: [ { id: 50639967936148, value: false }, { id: 41270881369364, value: false } ], comment: { body: 'Ticket de origem fechado automaticamente apos conclusao do ticket filho #' + $('Extrair Dados do Webhook').first().json.child_ticket_id + '. Agente: ' + ($('Extrair Dados do Webhook').first().json.agent_name || 'nao informado') + ' (' + ($('Extrair Dados do Webhook').first().json.agent_email || 'sem email') + ').', public: false } } }) }}",
        "options": {}
      },
      "id": "56ae8658-cfcc-4d8a-8f24-c25dea316971",
      "name": "Fechar Origem e Limpar Campos",
      "type": "n8n-nodes-base.httpRequest",
      "typeVersion": 4.2,
      "position": [
        896,
        160
      ],
      "credentials": {
        "httpHeaderAuth": {
          "id": "3csoYCJVQsP9ffsq",
          "name": "Zendesk API Header"
        }
      },
      "onError": "continueErrorOutput"
    },
    {
      "parameters": {
        "method": "DELETE",
        "url": "=https://webposto.zendesk.com/api/v2/tickets/{{ $('Extrair Dados do Webhook').first().json.origin_ticket_id }}/tags.json",
        "authentication": "genericCredentialType",
        "genericAuthType": "httpHeaderAuth",
        "sendBody": true,
        "specifyBody": "json",
        "jsonBody": "={{ JSON.stringify({ tags: ['impulsis_ativo'] }) }}",
        "options": {}
      },
      "id": "6875423e-5d4e-4a0c-afa0-8458d68a7533",
      "name": "Remover Tag impulsis_ativo",
      "type": "n8n-nodes-base.httpRequest",
      "typeVersion": 4.2,
      "position": [
        1120,
        96
      ],
      "credentials": {
        "httpHeaderAuth": {
          "id": "3csoYCJVQsP9ffsq",
          "name": "Zendesk API Header"
        }
      }
    },
    {
      "parameters": {
        "jsCode": "const wh = $('Extrair Dados do Webhook').first().json;\nconst child = $('Validar Ticket Filho Fechado').first().json;\nreturn [{ json: {\n  status: 'done',\n  origin_ticket_id: wh.origin_ticket_id,\n  child_ticket_id: wh.child_ticket_id,\n  child_status: child.child_status,\n  agent_name: wh.agent_name,\n  cleaned_field: true,\n  removed_tag: true,\n  origin_status_set: 'solved'\n} }];"
      },
      "id": "1603bb5c-0275-46e1-81d3-ba18f8eee9eb",
      "name": "Log Sucesso",
      "type": "n8n-nodes-base.code",
      "typeVersion": 2,
      "position": [
        1344,
        96
      ]
    },
    {
      "parameters": {
        "jsCode": "const wh = $('Extrair Dados do Webhook').first().json;\nreturn [{ json: {\n  status: 'skipped',\n  reason: wh.validation_error || 'invalid_payload',\n  payload: wh\n} }];"
      },
      "id": "489bad43-0a0f-4fdd-9c46-9424eccdce6f",
      "name": "Log Payload Invalido",
      "type": "n8n-nodes-base.code",
      "typeVersion": 2,
      "position": [
        0,
        448
      ]
    },
    {
      "parameters": {
        "url": "=https://webposto.zendesk.com/api/v2/tickets/{{ $json.child_ticket_id }}.json",
        "authentication": "genericCredentialType",
        "genericAuthType": "httpHeaderAuth",
        "options": {}
      },
      "id": "20d6cc3c-f698-4129-9b3e-ecfa85a12f6b",
      "name": "Buscar Ticket Filho",
      "type": "n8n-nodes-base.httpRequest",
      "typeVersion": 4.2,
      "position": [
        224,
        256
      ],
      "credentials": {
        "httpHeaderAuth": {
          "id": "3csoYCJVQsP9ffsq",
          "name": "Zendesk API Header"
        }
      }
    },
    {
      "parameters": {
        "jsCode": "const wh = $('Extrair Dados do Webhook').first().json;\nconst ticket = $input.first().json.ticket || {};\nconst child_status = ticket.status || '';\nconst child_is_closed = ['solved', 'closed'].includes(child_status);\n\nreturn [{ json: {\n  ...wh,\n  child_status,\n  child_is_closed,\n  child_subject: ticket.subject || '',\n  child_assignee_id: ticket.assignee_id || null\n} }];"
      },
      "id": "9ce3cab9-5062-43df-8a69-a8ccb89440b8",
      "name": "Validar Ticket Filho Fechado",
      "type": "n8n-nodes-base.code",
      "typeVersion": 2,
      "position": [
        448,
        256
      ]
    },
    {
      "parameters": {
        "conditions": {
          "options": {
            "caseSensitive": true,
            "leftValue": "",
            "typeValidation": "strict",
            "version": 2
          },
          "conditions": [
            {
              "id": "cond-child-closed",
              "leftValue": "={{ $json.child_is_closed }}",
              "rightValue": true,
              "operator": {
                "type": "boolean",
                "operation": "equals"
              }
            }
          ],
          "combinator": "and"
        },
        "options": {}
      },
      "id": "4ac72e9d-bcea-4f9c-8294-cfd07c130eb0",
      "name": "Filho Fechado",
      "type": "n8n-nodes-base.if",
      "typeVersion": 2.2,
      "position": [
        672,
        256
      ]
    },
    {
      "parameters": {
        "jsCode": "const wh = $('Extrair Dados do Webhook').first().json;\nconst child = $('Validar Ticket Filho Fechado').first().json;\nreturn [{ json: {\n  status: 'skipped',\n  reason: 'child_ticket_not_solved_or_closed',\n  origin_ticket_id: wh.origin_ticket_id,\n  child_ticket_id: wh.child_ticket_id,\n  child_status: child.child_status\n} }];"
      },
      "id": "b663a9ce-2ee3-4844-a56b-8f90d1c0a472",
      "name": "Log Filho Nao Fechado",
      "type": "n8n-nodes-base.code",
      "typeVersion": 2,
      "position": [
        896,
        448
      ]
    },
    {
      "parameters": {
        "respondWith": "json",
        "responseBody": "={{ $json }}",
        "options": {}
      },
      "id": "7a622cd3-5e7c-4ef2-9687-f6ec064f0913",
      "name": "Resposta Final Sucesso",
      "type": "n8n-nodes-base.respondToWebhook",
      "typeVersion": 1,
      "position": [
        1568,
        96
      ]
    },
    {
      "parameters": {
        "respondWith": "json",
        "responseBody": "={{ $json }}",
        "options": {}
      },
      "id": "8683956b-297f-464d-b0bf-4816a59da07e",
      "name": "Resposta Final Ignorado",
      "type": "n8n-nodes-base.respondToWebhook",
      "typeVersion": 1,
      "position": [
        1120,
        448
      ]
    },
    {
      "parameters": {
        "jsCode": "const wh = $('Extrair Dados do Webhook').first().json;\n\nfunction collectRaw(value, seen = new Set()) {\n  if (value === null || value === undefined) return [];\n  if (typeof value === 'string') return [value];\n  if (typeof value !== 'object') return [];\n  if (seen.has(value)) return [];\n  seen.add(value);\n\n  let out = [];\n  for (const v of Object.values(value)) {\n    out = out.concat(collectRaw(v, seen));\n  }\n  return out;\n}\n\nfunction tryParseJson(candidate) {\n  if (!candidate || typeof candidate !== 'string') return null;\n  const attempts = [\n    candidate,\n    candidate.replace(/\\\\\"/g, '\"'),\n    candidate.replace(/^\"|\"$/g, ''),\n    candidate.replace(/^\"|\"$/g, '').replace(/\\\\\"/g, '\"')\n  ];\n\n  for (const attempt of attempts) {\n    try {\n      const parsed = JSON.parse(attempt);\n      if (typeof parsed === 'string') {\n        const nested = tryParseJson(parsed);\n        if (nested) return nested;\n      }\n      if (parsed && typeof parsed === 'object') return parsed;\n    } catch (e) {}\n  }\n  return null;\n}\n\nfunction extractJsonObjects(raw) {\n  const candidates = [];\n  candidates.push(raw);\n\n  const firstBrace = raw.indexOf('{');\n  const lastBrace = raw.lastIndexOf('}');\n  if (firstBrace >= 0 && lastBrace > firstBrace) {\n    candidates.push(raw.slice(firstBrace, lastBrace + 1));\n  }\n\n  const firstQuoteBrace = raw.indexOf('\"{');\n  const lastBraceQuote = raw.lastIndexOf('}\"');\n  if (firstQuoteBrace >= 0 && lastBraceQuote > firstQuoteBrace) {\n    candidates.push(raw.slice(firstQuoteBrace + 1, lastBraceQuote + 1));\n  }\n\n  return candidates.map(tryParseJson).filter(Boolean);\n}\n\nconst rawStrings = collectRaw($json);\nconst parsedBodies = rawStrings.flatMap(extractJsonObjects);\n\nconst details = [];\nfor (const body of parsedBodies) {\n  const base = body.details && body.details.base;\n  if (Array.isArray(base)) details.push(...base);\n}\n\nfunction cleanFieldName(description) {\n  const text = String(description || 'Campo obrigatório pendente').trim();\n  const marker = ': é necessário';\n  if (text.includes(marker)) return text.split(marker)[0].trim();\n  return text.replace(/:.*$/, '').trim() || text;\n}\n\nconst missingFieldsRaw = details.map(d => {\n  const description = d.description || 'Campo obrigatório pendente';\n  return {\n    name: cleanFieldName(description),\n    description,\n    ticket_field_id: d.ticket_field_id || null,\n    ticket_field_type: d.ticket_field_type || null\n  };\n});\n\nconst seenFields = new Set();\nconst missingFields = [];\nfor (const field of missingFieldsRaw) {\n  const key = field.ticket_field_id ? `id:${field.ticket_field_id}` : `desc:${field.description}`;\n  if (seenFields.has(key)) continue;\n  seenFields.add(key);\n  missingFields.push(field);\n}\n\nconst missingText = missingFields.length\n  ? missingFields.map(f => `• ${f.name}`).join('\\n')\n  : '• Não foi possível extrair a lista de campos. Abra o ticket de origem e verifique os campos obrigatórios do formulário.';\n\nconst note = [\n  '⚠️ Origem não foi encerrada automaticamente',\n  '',\n  'O ticket filho #' + wh.child_ticket_id + ' foi encerrado, mas o Zendesk bloqueou o fechamento do ticket de origem #' + wh.origin_ticket_id + ' porque ainda existem campos obrigatórios pendentes.',\n  '',\n  'Preencha no ticket de origem:',\n  missingText,\n  '',\n  'Depois de preencher os campos obrigatórios no ticket de origem, aplique novamente a macro de encerramento neste ticket filho.',\n  'A macro remove a trava de reprocessamento e tenta fechar a origem novamente.'\n].join('\\n');\n\nreturn [{ json: {\n  status: 'origin_close_failed',\n  reason: 'zendesk_validation_error',\n  origin_ticket_id: wh.origin_ticket_id,\n  child_ticket_id: wh.child_ticket_id,\n  agent_name: wh.agent_name,\n  agent_email: wh.agent_email,\n  missing_fields: missingFields,\n  missing_fields_text: missingText,\n  nota_falha_fechamento: note,\n  raw_error: $json\n} }];"
      },
      "id": "c7ba968d-34f9-4ebe-b517-6daa313de032",
      "name": "Preparar Nota Falha Fechamento",
      "type": "n8n-nodes-base.code",
      "typeVersion": 2,
      "position": [
        1120,
        288
      ]
    },
    {
      "parameters": {
        "method": "PUT",
        "url": "=https://webposto.zendesk.com/api/v2/tickets/{{ $json.child_ticket_id }}.json",
        "authentication": "genericCredentialType",
        "genericAuthType": "httpHeaderAuth",
        "sendBody": true,
        "specifyBody": "json",
        "jsonBody": "={{ JSON.stringify({ ticket: { additional_tags: ['impulsis_falha_fechamento_origem'], comment: { body: $json.nota_falha_fechamento, public: false } } }) }}",
        "options": {}
      },
      "id": "639319ef-5966-45d7-89da-0900697f1e7a",
      "name": "Nota Falha no Ticket Filho",
      "type": "n8n-nodes-base.httpRequest",
      "typeVersion": 4.2,
      "position": [
        1344,
        288
      ],
      "credentials": {
        "httpHeaderAuth": {
          "id": "3csoYCJVQsP9ffsq",
          "name": "Zendesk API Header"
        }
      }
    },
    {
      "parameters": {
        "method": "PUT",
        "url": "=https://webposto.zendesk.com/api/v2/tickets/{{ $('Preparar Nota Falha Fechamento').first().json.origin_ticket_id }}.json",
        "authentication": "genericCredentialType",
        "genericAuthType": "httpHeaderAuth",
        "sendBody": true,
        "specifyBody": "json",
        "jsonBody": "={{ JSON.stringify({ ticket: { additional_tags: ['impulsis_pendencia_fechamento'], comment: { body: $('Preparar Nota Falha Fechamento').first().json.nota_falha_fechamento, public: false } } }) }}",
        "options": {}
      },
      "id": "a415a72f-d139-43c3-8405-289913f91371",
      "name": "Nota Falha no Ticket Original",
      "type": "n8n-nodes-base.httpRequest",
      "typeVersion": 4.2,
      "position": [
        1568,
        288
      ],
      "credentials": {
        "httpHeaderAuth": {
          "id": "3csoYCJVQsP9ffsq",
          "name": "Zendesk API Header"
        }
      }
    },
    {
      "parameters": {
        "jsCode": "const failure = $('Preparar Nota Falha Fechamento').first().json;\nreturn [{ json: {\n  status: 'origin_close_failed_notified',\n  origin_ticket_id: failure.origin_ticket_id,\n  child_ticket_id: failure.child_ticket_id,\n  missing_fields: failure.missing_fields,\n  notified_child: true,\n  notified_origin: true\n} }];"
      },
      "id": "d3f34129-4f78-4357-b7c4-f6c61d5d59d1",
      "name": "Log Falha Fechamento Notificada",
      "type": "n8n-nodes-base.code",
      "typeVersion": 2,
      "position": [
        1792,
        288
      ]
    }
  ],
  "connections": {
    "Webhook Fechar Origem": {
      "main": [
        [
          {
            "node": "Extrair Dados do Webhook",
            "type": "main",
            "index": 0
          }
        ]
      ]
    },
    "Extrair Dados do Webhook": {
      "main": [
        [
          {
            "node": "Payload Valido",
            "type": "main",
            "index": 0
          }
        ]
      ]
    },
    "Payload Valido": {
      "main": [
        [
          {
            "node": "Buscar Ticket Filho",
            "type": "main",
            "index": 0
          }
        ],
        [
          {
            "node": "Log Payload Invalido",
            "type": "main",
            "index": 0
          }
        ]
      ]
    },
    "Buscar Ticket Filho": {
      "main": [
        [
          {
            "node": "Validar Ticket Filho Fechado",
            "type": "main",
            "index": 0
          }
        ]
      ]
    },
    "Validar Ticket Filho Fechado": {
      "main": [
        [
          {
            "node": "Filho Fechado",
            "type": "main",
            "index": 0
          }
        ]
      ]
    },
    "Filho Fechado": {
      "main": [
        [
          {
            "node": "Fechar Origem e Limpar Campos",
            "type": "main",
            "index": 0
          }
        ],
        [
          {
            "node": "Log Filho Nao Fechado",
            "type": "main",
            "index": 0
          }
        ]
      ]
    },
    "Fechar Origem e Limpar Campos": {
      "main": [
        [
          {
            "node": "Remover Tag impulsis_ativo",
            "type": "main",
            "index": 0
          }
        ],
        [
          {
            "node": "Preparar Nota Falha Fechamento",
            "type": "main",
            "index": 0
          }
        ]
      ]
    },
    "Remover Tag impulsis_ativo": {
      "main": [
        [
          {
            "node": "Log Sucesso",
            "type": "main",
            "index": 0
          }
        ]
      ]
    },
    "Log Sucesso": {
      "main": [
        [
          {
            "node": "Resposta Final Sucesso",
            "type": "main",
            "index": 0
          }
        ]
      ]
    },
    "Log Payload Invalido": {
      "main": [
        [
          {
            "node": "Resposta Final Ignorado",
            "type": "main",
            "index": 0
          }
        ]
      ]
    },
    "Log Filho Nao Fechado": {
      "main": [
        [
          {
            "node": "Resposta Final Ignorado",
            "type": "main",
            "index": 0
          }
        ]
      ]
    },
    "Preparar Nota Falha Fechamento": {
      "main": [
        [
          {
            "node": "Nota Falha no Ticket Filho",
            "type": "main",
            "index": 0
          }
        ]
      ]
    },
    "Nota Falha no Ticket Filho": {
      "main": [
        [
          {
            "node": "Nota Falha no Ticket Original",
            "type": "main",
            "index": 0
          }
        ]
      ]
    },
    "Nota Falha no Ticket Original": {
      "main": [
        [
          {
            "node": "Log Falha Fechamento Notificada",
            "type": "main",
            "index": 0
          }
        ]
      ]
    },
    "Log Falha Fechamento Notificada": {
      "main": [
        [
          {
            "node": "Resposta Final Ignorado",
            "type": "main",
            "index": 0
          }
        ]
      ]
    }
  },
  "pinData": {
    "Webhook Fechar Origem": [
      {
        "headers": {
          "host": "webhook.qualityautomacao.com.br",
          "content-type": "application/json; charset=utf-8",
          "x-zendesk-account-id": "24752443",
          "x-zendesk-webhook-id": "01KVV4J8YMCR4Y539DA93K6EWH"
        },
        "params": {},
        "query": {},
        "body": {
          "action": "close_origin",
          "child_ticket_id": "118189",
          "origin_ticket_id": "116595",
          "agent_name": "Vinicius Gouvea",
          "agent_email": "vinicius.gouvea@webposto.com.br"
        },
        "webhookUrl": "https://webhook.qualityautomacao.com.br/webhook/impulsis-close-origin",
        "executionMode": "production"
      }
    ]
  },
  "meta": {
    "instanceId": "c6f86c928b1521171686fd64db45c641cb12e636101be3972a093c9cfcd6dc3d"
  },
  "name": "Impulsis - Fechar Origem v2 - seguro"
}